MANIFEST.in
README.rst
setup.py
sorl_url/__init__.py
sorl_url/models.py
sorl_url/signals.py
sorl_url/tests.py
sorl_url/urls.py
sorl_url/utils.py
sorl_url/views.py
sorl_url.egg-info/PKG-INFO
sorl_url.egg-info/SOURCES.txt
sorl_url.egg-info/dependency_links.txt
sorl_url.egg-info/not-zip-safe
sorl_url.egg-info/top_level.txt
sorl_url/templates/sorl_url/debug.html
sorl_url/templatetags/__init__.py
sorl_url/templatetags/image_url.py