Metadata-Version: 1.0
Name: sorl-url
Version: 0.1.8
Summary: Out-of-band processing for sorl-thumbnail thumbnails.
Home-page: https://github.com/bolster/sorl-url
Author: Bolster Labs, Inc
Author-email: opensource@boslterlabs.com
License: BSD
Platform: any
Classifier: Development Status :: 4 - Beta
Classifier: Environment :: Web Environment
Classifier: Intended Audience :: Developers
Classifier: License :: OSI Approved :: BSD License
Classifier: Operating System :: OS Independent
Classifier: Programming Language :: Python
Classifier: Topic :: Internet :: WWW/HTTP :: Dynamic Content
Classifier: Topic :: Multimedia :: Graphics
Classifier: Framework :: Django
